snowmover/__init__.py
snowmover-0.0.1a0.dist-info/licenses/LICENSE
snowmover-0.0.1a0.dist-info/METADATA
snowmover-0.0.1a0.dist-info/WHEEL
snowmover-0.0.1a0.dist-info/top_level.txt
snowmover-0.0.1a0.dist-info/RECORD
