Metadata-Version: 2.4
Name: snowmover
Version: 0.0.1a0
Summary: A lightweight Python toolkit for Snowflake data moves: upload local text files with PUT/COPY INTO, row-by-row inserts, extract tables to local files (TXT/CSV/Excel), Snowflake-to-Snowflake transfers, and simple, secure connection helpers.
Author: Harjinder Sidhu
License: MIT
Keywords: Python,open-source,snowflake,snowflake-connector,data-loader,data-pipeline,etl,data-ingestion,data-export,data-engineering,data-warehouse,database-tools
Requires-Python: >=3.10
License-File: LICENSE
Dynamic: license-file
